{"website_domain":"https://rakuten.co.jp","post_pageload_url":"https://www.rakuten.co.jp/","pageload_start_ts":1686141557048,"pageload_end_ts":1686141567242,"requests":[{":authority":"r.r10s.jp",":method":"GET",":path":"/com/js/d/Rmodules/modules/rmod-jquery-1.12.2.min.js",":scheme":"https","accept":"*/*","accept-encoding":"gzip, deflate, br","referer":"https://www.rakuten.co.jp/","sec-ch-ua":"\"Not.A/Brand\";v=\"8\", \"Chromium\";v=\"114\", \"HeadlessChrome\";v=\"114\"","sec-ch-ua-mobile":"?0","sec-ch-ua-platform":"\"macOS\"","sec-fetch-dest":"script","sec-fetch-mode":"no-cors","sec-fetch-site":"cross-site","user-agent":"Mozilla/5.0 (Macintosh; Intel Mac OS X 10_15_7) AppleWebKit/537.36 (KHTML, like Gecko) HeadlessChrome/114.0.5735.35 Safari/537.36"},{":authority":"r.r10s.jp",":method":"GET",":path":"/com/js/d/R/1.7/R-1.7.1.min.js",":scheme":"https","accept":"*/*","accept-encoding":"gzip, deflate, br","referer":"https://www.rakuten.co.jp/","sec-ch-ua":"\"Not.A/Brand\";v=\"8\", \"Chromium\";v=\"114\", \"HeadlessChrome\";v=\"114\"","sec-ch-ua-mobile":"?0","sec-ch-ua-platform":"\"macOS\"","sec-fetch-dest":"script","sec-fetch-mode":"no-cors","sec-fetch-site":"cross-site","user-agent":"Mozilla/5.0 (Macintosh; Intel Mac OS X 10_15_7) AppleWebKit/537.36 (KHTML, like Gecko) HeadlessChrome/114.0.5735.35 Safari/537.36"},{":authority":"r.r10s.jp",":method":"GET",":path":"/com/js/d/RApiTop/1.7/R.api.top-1.7.1.min.js",":scheme":"https","accept":"*/*","accept-encoding":"gzip, deflate, br","referer":"https://www.rakuten.co.jp/","sec-ch-ua":"\"Not.A/Brand\";v=\"8\", \"Chromium\";v=\"114\", \"HeadlessChrome\";v=\"114\"","sec-ch-ua-mobile":"?0","sec-ch-ua-platform":"\"macOS\"","sec-fetch-dest":"script","sec-fetch-mode":"no-cors","sec-fetch-site":"cross-site","user-agent":"Mozilla/5.0 (Macintosh; Intel Mac OS X 10_15_7) AppleWebKit/537.36 (KHTML, like Gecko) HeadlessChrome/114.0.5735.35 Safari/537.36"},{":authority":"r.r10s.jp",":method":"GET",":path":"/com/js/d/RUi/1.4/R.ui-1.4.1.min.js",":scheme":"https","accept":"*/*","accept-encoding":"gzip, deflate, br","referer":"https://www.rakuten.co.jp/","sec-ch-ua":"\"Not.A/Brand\";v=\"8\", \"Chromium\";v=\"114\", \"HeadlessChrome\";v=\"114\"","sec-ch-ua-mobile":"?0","sec-ch-ua-platform":"\"macOS\"","sec-fetch-dest":"script","sec-fetch-mode":"no-cors","sec-fetch-site":"cross-site","user-agent":"Mozilla/5.0 (Macintosh; Intel Mac OS X 10_15_7) AppleWebKit/537.36 (KHTML, like Gecko) HeadlessChrome/114.0.5735.35 Safari/537.36"},{":authority":"r.r10s.jp",":method":"GET",":path":"/com/inc/home/20080930/spt/common/img/icon_sprite_09.png",":scheme":"https","accept":"image/avif,image/webp,image/apng,image/svg+xml,image/*,*/*;q=0.8","accept-encoding":"gzip, deflate, br","referer":"https://r.r10s.jp/com/inc/home/20080930/spt/common/css/develop_js_1.1.1.min.css?v=20220517","sec-ch-ua":"\"Not.A/Brand\";v=\"8\", \"Chromium\";v=\"114\", \"HeadlessChrome\";v=\"114\"","sec-ch-ua-mobile":"?0","sec-ch-ua-platform":"\"macOS\"","sec-fetch-dest":"image","sec-fetch-mode":"no-cors","sec-fetch-site":"cross-site","user-agent":"Mozilla/5.0 (Macintosh; Intel Mac OS X 10_15_7) AppleWebKit/537.36 (KHTML, like Gecko) HeadlessChrome/114.0.5735.35 Safari/537.36"},{":authority":"r.r10s.jp",":method":"GET",":path":"/com/inc/home/20080930/spt/common/img/notification/icon_notice.svg",":scheme":"https","accept":"image/avif,image/webp,image/apng,image/svg+xml,image/*,*/*;q=0.8","accept-encoding":"gzip, deflate, br","referer":"https://r.r10s.jp/com/inc/home/20080930/spt/common/css/ichiba_top-1.2.2.min.css?v=20220810","sec-ch-ua":"\"Not.A/Brand\";v=\"8\", \"Chromium\";v=\"114\", \"HeadlessChrome\";v=\"114\"","sec-ch-ua-mobile":"?0","sec-ch-ua-platform":"\"macOS\"","sec-fetch-dest":"image","sec-fetch-mode":"no-cors","sec-fetch-site":"cross-site","user-agent":"Mozilla/5.0 (Macintosh; Intel Mac OS X 10_15_7) AppleWebKit/537.36 (KHTML, like Gecko) HeadlessChrome/114.0.5735.35 Safari/537.36"},{":authority":"r.r10s.jp",":method":"GET",":path":"/com/inc/home/20080930/spt/common/img/footer_anshin.png",":scheme":"https","accept":"image/avif,image/webp,image/apng,image/svg+xml,image/*,*/*;q=0.8","accept-encoding":"gzip, deflate, br","referer":"https://r.r10s.jp/com/inc/home/20080930/spt/common/css/ichiba_top-1.2.2.min.css?v=20220810","sec-ch-ua":"\"Not.A/Brand\";v=\"8\", \"Chromium\";v=\"114\", \"HeadlessChrome\";v=\"114\"","sec-ch-ua-mobile":"?0","sec-ch-ua-platform":"\"macOS\"","sec-fetch-dest":"image","sec-fetch-mode":"no-cors","sec-fetch-site":"cross-site","user-agent":"Mozilla/5.0 (Macintosh; Intel Mac OS X 10_15_7) AppleWebKit/537.36 (KHTML, like Gecko) HeadlessChrome/114.0.5735.35 Safari/537.36"},{":authority":"r.r10s.jp",":method":"GET",":path":"/com/inc/home/20080930/beta/tz/img/footer/footer_cart.png",":scheme":"https","accept":"image/avif,image/webp,image/apng,image/svg+xml,image/*,*/*;q=0.8","accept-encoding":"gzip, deflate, br","referer":"https://r.r10s.jp/com/inc/home/20080930/spt/common/css/ichiba_top-1.2.2.min.css?v=20220810","sec-ch-ua":"\"Not.A/Brand\";v=\"8\", \"Chromium\";v=\"114\", \"HeadlessChrome\";v=\"114\"","sec-ch-ua-mobile":"?0","sec-ch-ua-platform":"\"macOS\"","sec-fetch-dest":"image","sec-fetch-mode":"no-cors","sec-fetch-site":"cross-site","user-agent":"Mozilla/5.0 (Macintosh; Intel Mac OS X 10_15_7) AppleWebKit/537.36 (KHTML, like Gecko) HeadlessChrome/114.0.5735.35 Safari/537.36"},{":authority":"r.r10s.jp",":method":"GET",":path":"/com/inc/home/20080930/spt/common/img/footer_csr.png",":scheme":"https","accept":"image/avif,image/webp,image/apng,image/svg+xml,image/*,*/*;q=0.8","accept-encoding":"gzip, deflate, br","referer":"https://r.r10s.jp/com/inc/home/20080930/spt/common/css/ichiba_top-1.2.2.min.css?v=20220810","sec-ch-ua":"\"Not.A/Brand\";v=\"8\", \"Chromium\";v=\"114\", \"HeadlessChrome\";v=\"114\"","sec-ch-ua-mobile":"?0","sec-ch-ua-platform":"\"macOS\"","sec-fetch-dest":"image","sec-fetch-mode":"no-cors","sec-fetch-site":"cross-site","user-agent":"Mozilla/5.0 (Macintosh; Intel Mac OS X 10_15_7) AppleWebKit/537.36 (KHTML, like Gecko) HeadlessChrome/114.0.5735.35 Safari/537.36"},{":authority":"r.r10s.jp",":method":"GET",":path":"/com/inc/home/20080930/spt/common/img/notification/icon_chevron_right.svg",":scheme":"https","accept":"image/avif,image/webp,image/apng,image/svg+xml,image/*,*/*;q=0.8","accept-encoding":"gzip, deflate, br","referer":"https://r.r10s.jp/com/inc/home/20080930/spt/common/css/ichiba_top-1.2.2.min.css?v=20220810","sec-ch-ua":"\"Not.A/Brand\";v=\"8\", \"Chromium\";v=\"114\", \"HeadlessChrome\";v=\"114\"","sec-ch-ua-mobile":"?0","sec-ch-ua-platform":"\"macOS\"","sec-fetch-dest":"image","sec-fetch-mode":"no-cors","sec-fetch-site":"cross-site","user-agent":"Mozilla/5.0 (Macintosh; Intel Mac OS X 10_15_7) AppleWebKit/537.36 (KHTML, like Gecko) HeadlessChrome/114.0.5735.35 Safari/537.36"},{":authority":"r.r10s.jp",":method":"GET",":path":"/com/inc/home/20080930/spt/common/img/footer_shop.png",":scheme":"https","accept":"image/avif,image/webp,image/apng,image/svg+xml,image/*,*/*;q=0.8","accept-encoding":"gzip, deflate, br","referer":"https://r.r10s.jp/com/inc/home/20080930/spt/common/css/ichiba_top-1.2.2.min.css?v=20220810","sec-ch-ua":"\"Not.A/Brand\";v=\"8\", \"Chromium\";v=\"114\", \"HeadlessChrome\";v=\"114\"","sec-ch-ua-mobile":"?0","sec-ch-ua-platform":"\"macOS\"","sec-fetch-dest":"image","sec-fetch-mode":"no-cors","sec-fetch-site":"cross-site","user-agent":"Mozilla/5.0 (Macintosh; Intel Mac OS X 10_15_7) AppleWebKit/537.36 (KHTML, like Gecko) HeadlessChrome/114.0.5735.35 Safari/537.36"},{":authority":"image.rakuten.co.jp",":method":"GET",":path":"/com/img/home/t.gif",":scheme":"https","accept":"image/avif,image/webp,image/apng,image/svg+xml,image/*,*/*;q=0.8","accept-encoding":"gzip, deflate, br","referer":"https://www.rakuten.co.jp/","sec-ch-ua":"\"Not.A/Brand\";v=\"8\", \"Chromium\";v=\"114\", \"HeadlessChrome\";v=\"114\"","sec-ch-ua-mobile":"?0","sec-ch-ua-platform":"\"macOS\"","sec-fetch-dest":"image","sec-fetch-mode":"no-cors","sec-fetch-site":"same-site","user-agent":"Mozilla/5.0 (Macintosh; Intel Mac OS X 10_15_7) AppleWebKit/537.36 (KHTML, like Gecko) HeadlessChrome/114.0.5735.35 Safari/537.36"},{":authority":"fonts.gstatic.com",":method":"GET",":path":"/l/font?kit=KFOlCnqEu92Fr1MmSU5vBh0_IsHAnqd-SkmHNWwpVAzh&skey=11ce8ad5f54705ca&v=v30",":scheme":"https","accept":"*/*","accept-encoding":"gzip, deflate, br","origin":"https://www.rakuten.co.jp","referer":"https://fonts.googleapis.com/","sec-ch-ua":"\"Not.A/Brand\";v=\"8\", \"Chromium\";v=\"114\", \"HeadlessChrome\";v=\"114\"","sec-ch-ua-mobile":"?0","sec-ch-ua-platform":"\"macOS\"","sec-fetch-dest":"font","sec-fetch-mode":"cors","sec-fetch-site":"cross-site","user-agent":"Mozilla/5.0 (Macintosh; Intel Mac OS X 10_15_7) AppleWebKit/537.36 (KHTML, like Gecko) HeadlessChrome/114.0.5735.35 Safari/537.36"},{":authority":"fonts.gstatic.com",":method":"GET",":path":"/l/font?kit=KFOlCnqEu92Fr1MmEU9vBh0_IsHAnqd-SkmHNWwpVAzh&skey=ee881451c540fdec&v=v30",":scheme":"https","accept":"*/*","accept-encoding":"gzip, deflate, br","origin":"https://www.rakuten.co.jp","referer":"https://fonts.googleapis.com/","sec-ch-ua":"\"Not.A/Brand\";v=\"8\", \"Chromium\";v=\"114\", \"HeadlessChrome\";v=\"114\"","sec-ch-ua-mobile":"?0","sec-ch-ua-platform":"\"macOS\"","sec-fetch-dest":"font","sec-fetch-mode":"cors","sec-fetch-site":"cross-site","user-agent":"Mozilla/5.0 (Macintosh; Intel Mac OS X 10_15_7) AppleWebKit/537.36 (KHTML, like Gecko) HeadlessChrome/114.0.5735.35 Safari/537.36"},{":authority":"gettime.r10s.jp",":method":"GET",":path":"/?callback=jsonp1686141562306",":scheme":"https","accept":"*/*","accept-encoding":"gzip, deflate, br","referer":"https://www.rakuten.co.jp/","sec-ch-ua":"\"Not.A/Brand\";v=\"8\", \"Chromium\";v=\"114\", \"HeadlessChrome\";v=\"114\"","sec-ch-ua-mobile":"?0","sec-ch-ua-platform":"\"macOS\"","sec-fetch-dest":"script","sec-fetch-mode":"no-cors","sec-fetch-site":"cross-site","user-agent":"Mozilla/5.0 (Macintosh; Intel Mac OS X 10_15_7) AppleWebKit/537.36 (KHTML, like Gecko) HeadlessChrome/114.0.5735.35 Safari/537.36"},{":authority":"r.r10s.jp",":method":"GET",":path":"/com/inc/home/20080930/spt/common/img/new_icon.svg",":scheme":"https","accept":"image/avif,image/webp,image/apng,image/svg+xml,image/*,*/*;q=0.8","accept-encoding":"gzip, deflate, br","referer":"https://www.rakuten.co.jp/","sec-ch-ua":"\"Not.A/Brand\";v=\"8\", \"Chromium\";v=\"114\", \"HeadlessChrome\";v=\"114\"","sec-ch-ua-mobile":"?0","sec-ch-ua-platform":"\"macOS\"","sec-fetch-dest":"image","sec-fetch-mode":"no-cors","sec-fetch-site":"cross-site","user-agent":"Mozilla/5.0 (Macintosh; Intel Mac OS X 10_15_7) AppleWebKit/537.36 (KHTML, like Gecko) HeadlessChrome/114.0.5735.35 Safari/537.36"},{":authority":"r.r10s.jp",":method":"GET",":path":"/com/inc/smart/fonts/2.1.0/ri-iconfont.ttf?9mpo4l",":scheme":"https","accept":"*/*","accept-encoding":"gzip, deflate, br","origin":"https://www.rakuten.co.jp","referer":"https://r.r10s.jp/com/inc/home/20080930/spt/common/css/ichiba_top-1.2.2.min.css?v=20220810","sec-ch-ua":"\"Not.A/Brand\";v=\"8\", \"Chromium\";v=\"114\", \"HeadlessChrome\";v=\"114\"","sec-ch-ua-mobile":"?0","sec-ch-ua-platform":"\"macOS\"","sec-fetch-dest":"font","sec-fetch-mode":"cors","sec-fetch-site":"cross-site","user-agent":"Mozilla/5.0 (Macintosh; Intel Mac OS X 10_15_7) AppleWebKit/537.36 (KHTML, like Gecko) HeadlessChrome/114.0.5735.35 Safari/537.36"},{":authority":"r.r10s.jp",":method":"GET",":path":"/com/js/d/RApi/1.16/R.api-1.16.3.min.js",":scheme":"https","accept":"*/*","accept-encoding":"gzip, deflate, br","referer":"https://www.rakuten.co.jp/","sec-ch-ua":"\"Not.A/Brand\";v=\"8\", \"Chromium\";v=\"114\", \"HeadlessChrome\";v=\"114\"","sec-ch-ua-mobile":"?0","sec-ch-ua-platform":"\"macOS\"","sec-fetch-dest":"script","sec-fetch-mode":"no-cors","sec-fetch-site":"cross-site","user-agent":"Mozilla/5.0 (Macintosh; Intel Mac OS X 10_15_7) AppleWebKit/537.36 (KHTML, like Gecko) HeadlessChrome/114.0.5735.35 Safari/537.36"},{":authority":"r.r10s.jp",":method":"GET",":path":"/com/entf/asset/css/entf-2.1.0.css?20170531",":scheme":"https","accept":"text/css,*/*;q=0.1","accept-encoding":"gzip, deflate, br","referer":"https://www.rakuten.co.jp/","sec-ch-ua":"\"Not.A/Brand\";v=\"8\", \"Chromium\";v=\"114\", \"HeadlessChrome\";v=\"114\"","sec-ch-ua-mobile":"?0","sec-ch-ua-platform":"\"macOS\"","sec-fetch-dest":"style","sec-fetch-mode":"no-cors","sec-fetch-site":"cross-site","user-agent":"Mozilla/5.0 (Macintosh; Intel Mac OS X 10_15_7) AppleWebKit/537.36 (KHTML, like Gecko) HeadlessChrome/114.0.5735.35 Safari/537.36"},{":authority":"r.r10s.jp",":method":"GET",":path":"/com/assets/resources/r-logo168bc44f5e8c64e9f566a4e10668c7a6.svg",":scheme":"https","accept":"image/avif,image/webp,image/apng,image/svg+xml,image/*,*/*;q=0.8","accept-encoding":"gzip, deflate, br","referer":"https://r.r10s.jp/com/assets/app/pages/top/css/pc~touch-3f5bf962407f13b2b8f2.bundle.css","sec-ch-ua":"\"Not.A/Brand\";v=\"8\", \"Chromium\";v=\"114\", \"HeadlessChrome\";v=\"114\"","sec-ch-ua-mobile":"?0","sec-ch-ua-platform":"\"macOS\"","sec-fetch-dest":"image","sec-fetch-mode":"no-cors","sec-fetch-site":"cross-site","user-agent":"Mozilla/5.0 (Macintosh; Intel Mac OS X 10_15_7) AppleWebKit/537.36 (KHTML, like Gecko) HeadlessChrome/114.0.5735.35 Safari/537.36"},{":authority":"r.r10s.jp",":method":"GET",":path":"/com/rat/js/ral-1.0.21-dui-1.js",":scheme":"https","accept":"*/*","accept-encoding":"gzip, deflate, br","referer":"https://www.rakuten.co.jp/","sec-ch-ua":"\"Not.A/Brand\";v=\"8\", \"Chromium\";v=\"114\", \"HeadlessChrome\";v=\"114\"","sec-ch-ua-mobile":"?0","sec-ch-ua-platform":"\"macOS\"","sec-fetch-dest":"script","sec-fetch-mode":"no-cors","sec-fetch-site":"cross-site","user-agent":"Mozilla/5.0 (Macintosh; Intel Mac OS X 10_15_7) AppleWebKit/537.36 (KHTML, like Gecko) HeadlessChrome/114.0.5735.35 Safari/537.36"},{":authority":"r.r10s.jp",":method":"GET",":path":"/com/assets/resources/supersale-pc9234f3f5e2e382f95e6f7c3452ec827f.svg",":scheme":"https","accept":"image/avif,image/webp,image/apng,image/svg+xml,image/*,*/*;q=0.8","accept-encoding":"gzip, deflate, br","referer":"https://r.r10s.jp/com/assets/app/pages/top/css/pc~touch-3f5bf962407f13b2b8f2.bundle.css","sec-ch-ua":"\"Not.A/Brand\";v=\"8\", \"Chromium\";v=\"114\", \"HeadlessChrome\";v=\"114\"","sec-ch-ua-mobile":"?0","sec-ch-ua-platform":"\"macOS\"","sec-fetch-dest":"image","sec-fetch-mode":"no-cors","sec-fetch-site":"cross-site","user-agent":"Mozilla/5.0 (Macintosh; Intel Mac OS X 10_15_7) AppleWebKit/537.36 (KHTML, like Gecko) HeadlessChrome/114.0.5735.35 Safari/537.36"},{":authority":"r.r10s.jp",":method":"GET",":path":"/com/img/thumb/200309/message/flash/campaign/bigsaleparts/list/bigsale_bulk.jpg",":scheme":"https","accept":"image/avif,image/webp,image/apng,image/svg+xml,image/*,*/*;q=0.8","accept-encoding":"gzip, deflate, br","referer":"https://www.rakuten.co.jp/","sec-ch-ua":"\"Not.A/Brand\";v=\"8\", \"Chromium\";v=\"114\", \"HeadlessChrome\";v=\"114\"","sec-ch-ua-mobile":"?0","sec-ch-ua-platform":"\"macOS\"","sec-fetch-dest":"image","sec-fetch-mode":"no-cors","sec-fetch-site":"cross-site","user-agent":"Mozilla/5.0 (Macintosh; Intel Mac OS X 10_15_7) AppleWebKit/537.36 (KHTML, like Gecko) HeadlessChrome/114.0.5735.35 Safari/537.36"},{":authority":"r.r10s.jp",":method":"GET",":path":"/com/img/thumb/200309/message/flash/campaign/bigsaleparts/title/panda_ss.svg",":scheme":"https","accept":"image/avif,image/webp,image/apng,image/svg+xml,image/*,*/*;q=0.8","accept-encoding":"gzip, deflate, br","referer":"https://www.rakuten.co.jp/","sec-ch-ua":"\"Not.A/Brand\";v=\"8\", \"Chromium\";v=\"114\", \"HeadlessChrome\";v=\"114\"","sec-ch-ua-mobile":"?0","sec-ch-ua-platform":"\"macOS\"","sec-fetch-dest":"image","sec-fetch-mode":"no-cors","sec-fetch-site":"cross-site","user-agent":"Mozilla/5.0 (Macintosh; Intel Mac OS X 10_15_7) AppleWebKit/537.36 (KHTML, like Gecko) HeadlessChrome/114.0.5735.35 Safari/537.36"},{":authority":"r.r10s.jp",":method":"GET",":path":"/com/img/thumb/200309/message/flash/campaign/bigsaleparts/list/bigsale_bigsale.jpg",":scheme":"https","accept":"image/avif,image/webp,image/apng,image/svg+xml,image/*,*/*;q=0.8","accept-encoding":"gzip, deflate, br","referer":"https://www.rakuten.co.jp/","sec-ch-ua":"\"Not.A/Brand\";v=\"8\", \"Chromium\";v=\"114\", \"HeadlessChrome\";v=\"114\"","sec-ch-ua-mobile":"?0","sec-ch-ua-platform":"\"macOS\"","sec-fetch-dest":"image","sec-fetch-mode":"no-cors","sec-fetch-site":"cross-site","user-agent":"Mozilla/5.0 (Macintosh; Intel Mac OS X 10_15_7) AppleWebKit/537.36 (KHTML, like Gecko) HeadlessChrome/114.0.5735.35 Safari/537.36"},{":authority":"r.r10s.jp",":method":"GET",":path":"/com/img/thumb/200309/message/flash/campaign/bigsaleparts/list/202306_ss_appliance-festival_bn2_10_160x160.jpg",":scheme":"https","accept":"image/avif,image/webp,image/apng,image/svg+xml,image/*,*/*;q=0.8","accept-encoding":"gzip, deflate, br","referer":"https://www.rakuten.co.jp/","sec-ch-ua":"\"Not.A/Brand\";v=\"8\", \"Chromium\";v=\"114\", \"HeadlessChrome\";v=\"114\"","sec-ch-ua-mobile":"?0","sec-ch-ua-platform":"\"macOS\"","sec-fetch-dest":"image","sec-fetch-mode":"no-cors","sec-fetch-site":"cross-site","user-agent":"Mozilla/5.0 (Macintosh; Intel Mac OS X 10_15_7) AppleWebKit/537.36 (KHTML, like Gecko) HeadlessChrome/114.0.5735.35 Safari/537.36"},{":authority":"r.r10s.jp",":method":"GET",":path":"/com/assets/resources/ichiba-icon-font83b762bd095120983fe2067eee3b4de4.woff",":scheme":"https","accept":"*/*","accept-encoding":"gzip, deflate, br","origin":"https://www.rakuten.co.jp","referer":"https://r.r10s.jp/com/assets/app/pages/top/css/pc~touch-3f5bf962407f13b2b8f2.bundle.css","sec-ch-ua":"\"Not.A/Brand\";v=\"8\", \"Chromium\";v=\"114\", \"HeadlessChrome\";v=\"114\"","sec-ch-ua-mobile":"?0","sec-ch-ua-platform":"\"macOS\"","sec-fetch-dest":"font","sec-fetch-mode":"cors","sec-fetch-site":"cross-site","user-agent":"Mozilla/5.0 (Macintosh; Intel Mac OS X 10_15_7) AppleWebKit/537.36 (KHTML, like Gecko) HeadlessChrome/114.0.5735.35 Safari/537.36"},{":authority":"r.r10s.jp",":method":"GET",":path":"/com/img/home/opt/css/icn_close_gray.gif",":scheme":"https","accept":"image/avif,image/webp,image/apng,image/svg+xml,image/*,*/*;q=0.8","accept-encoding":"gzip, deflate, br","referer":"https://www.rakuten.co.jp/","sec-ch-ua":"\"Not.A/Brand\";v=\"8\", \"Chromium\";v=\"114\", \"HeadlessChrome\";v=\"114\"","sec-ch-ua-mobile":"?0","sec-ch-ua-platform":"\"macOS\"","sec-fetch-dest":"image","sec-fetch-mode":"no-cors","sec-fetch-site":"cross-site","user-agent":"Mozilla/5.0 (Macintosh; Intel Mac OS X 10_15_7) AppleWebKit/537.36 (KHTML, like Gecko) HeadlessChrome/114.0.5735.35 Safari/537.36"},{":authority":"r.r10s.jp",":method":"GET",":path":"/com/img/thumb/200309/message/flash/campaign/bigsaleparts/list/202306_ss_brandcosme_19_160x160.jpg",":scheme":"https","accept":"image/avif,image/webp,image/apng,image/svg+xml,image/*,*/*;q=0.8","accept-encoding":"gzip, deflate, br","referer":"https://www.rakuten.co.jp/","sec-ch-ua":"\"Not.A/Brand\";v=\"8\", \"Chromium\";v=\"114\", \"HeadlessChrome\";v=\"114\"","sec-ch-ua-mobile":"?0","sec-ch-ua-platform":"\"macOS\"","sec-fetch-dest":"image","sec-fetch-mode":"no-cors","sec-fetch-site":"cross-site","user-agent":"Mozilla/5.0 (Macintosh; Intel Mac OS X 10_15_7) AppleWebKit/537.36 (KHTML, like Gecko) HeadlessChrome/114.0.5735.35 Safari/537.36"},{":authority":"tshop.r10s.jp",":method":"GET",":path":"/casetify/logo/logo1.jpg?fitin=200:200",":scheme":"https","accept":"image/avif,image/webp,image/apng,image/svg+xml,image/*,*/*;q=0.8","accept-encoding":"gzip, deflate, br","referer":"https://www.rakuten.co.jp/","sec-ch-ua":"\"Not.A/Brand\";v=\"8\", \"Chromium\";v=\"114\", \"HeadlessChrome\";v=\"114\"","sec-ch-ua-mobile":"?0","sec-ch-ua-platform":"\"macOS\"","sec-fetch-dest":"image","sec-fetch-mode":"no-cors","sec-fetch-site":"cross-site","user-agent":"Mozilla/5.0 (Macintosh; Intel Mac OS X 10_15_7) AppleWebKit/537.36 (KHTML, like Gecko) HeadlessChrome/114.0.5735.35 Safari/537.36"},{":authority":"tshop.r10s.jp",":method":"GET",":path":"/minnetonka/logo/logo1.jpg?fitin=200:200",":scheme":"https","accept":"image/avif,image/webp,image/apng,image/svg+xml,image/*,*/*;q=0.8","accept-encoding":"gzip, deflate, br","referer":"https://www.rakuten.co.jp/","sec-ch-ua":"\"Not.A/Brand\";v=\"8\", \"Chromium\";v=\"114\", \"HeadlessChrome\";v=\"114\"","sec-ch-ua-mobile":"?0","sec-ch-ua-platform":"\"macOS\"","sec-fetch-dest":"image","sec-fetch-mode":"no-cors","sec-fetch-site":"cross-site","user-agent":"Mozilla/5.0 (Macintosh; Intel Mac OS X 10_15_7) AppleWebKit/537.36 (KHTML, like Gecko) HeadlessChrome/114.0.5735.35 Safari/537.36"},{":authority":"tshop.r10s.jp",":method":"GET",":path":"/lindt-chocolate/logo/logo1.jpg?fitin=200:200",":scheme":"https","accept":"image/avif,image/webp,image/apng,image/svg+xml,image/*,*/*;q=0.8","accept-encoding":"gzip, deflate, br","referer":"https://www.rakuten.co.jp/","sec-ch-ua":"\"Not.A/Brand\";v=\"8\", \"Chromium\";v=\"114\", \"HeadlessChrome\";v=\"114\"","sec-ch-ua-mobile":"?0","sec-ch-ua-platform":"\"macOS\"","sec-fetch-dest":"image","sec-fetch-mode":"no-cors","sec-fetch-site":"cross-site","user-agent":"Mozilla/5.0 (Macintosh; Intel Mac OS X 10_15_7) AppleWebKit/537.36 (KHTML, like Gecko) HeadlessChrome/114.0.5735.35 Safari/537.36"},{":authority":"tshop.r10s.jp",":method":"GET",":path":"/nec-direct/logo/logo1.jpg?fitin=200:200",":scheme":"https","accept":"image/avif,image/webp,image/apng,image/svg+xml,image/*,*/*;q=0.8","accept-encoding":"gzip, deflate, br","referer":"https://www.rakuten.co.jp/","sec-ch-ua":"\"Not.A/Brand\";v=\"8\", \"Chromium\";v=\"114\", \"HeadlessChrome\";v=\"114\"","sec-ch-ua-mobile":"?0","sec-ch-ua-platform":"\"macOS\"","sec-fetch-dest":"image","sec-fetch-mode":"no-cors","sec-fetch-site":"cross-site","user-agent":"Mozilla/5.0 (Macintosh; Intel Mac OS X 10_15_7) AppleWebKit/537.36 (KHTML, like Gecko) HeadlessChrome/114.0.5735.35 Safari/537.36"},{":authority":"tshop.r10s.jp",":method":"GET",":path":"/kikusui/logo/logo1.jpg?fitin=200:200",":scheme":"https","accept":"image/avif,image/webp,image/apng,image/svg+xml,image/*,*/*;q=0.8","accept-encoding":"gzip, deflate, br","referer":"https://www.rakuten.co.jp/","sec-ch-ua":"\"Not.A/Brand\";v=\"8\", \"Chromium\";v=\"114\", \"HeadlessChrome\";v=\"114\"","sec-ch-ua-mobile":"?0","sec-ch-ua-platform":"\"macOS\"","sec-fetch-dest":"image","sec-fetch-mode":"no-cors","sec-fetch-site":"cross-site","user-agent":"Mozilla/5.0 (Macintosh; Intel Mac OS X 10_15_7) AppleWebKit/537.36 (KHTML, like Gecko) HeadlessChrome/114.0.5735.35 Safari/537.36"},{":authority":"tshop.r10s.jp",":method":"GET",":path":"/primaham/logo/logo1.jpg?fitin=200:200",":scheme":"https","accept":"image/avif,image/webp,image/apng,image/svg+xml,image/*,*/*;q=0.8","accept-encoding":"gzip, deflate, br","referer":"https://www.rakuten.co.jp/","sec-ch-ua":"\"Not.A/Brand\";v=\"8\", \"Chromium\";v=\"114\", \"HeadlessChrome\";v=\"114\"","sec-ch-ua-mobile":"?0","sec-ch-ua-platform":"\"macOS\"","sec-fetch-dest":"image","sec-fetch-mode":"no-cors","sec-fetch-site":"cross-site","user-agent":"Mozilla/5.0 (Macintosh; Intel Mac OS X 10_15_7) AppleWebKit/537.36 (KHTML, like Gecko) HeadlessChrome/114.0.5735.35 Safari/537.36"},{":authority":"tshop.r10s.jp",":method":"GET",":path":"/pocketalk-official/logo/logo1.jpg?fitin=200:200",":scheme":"https","accept":"image/avif,image/webp,image/apng,image/svg+xml,image/*,*/*;q=0.8","accept-encoding":"gzip, deflate, br","referer":"https://www.rakuten.co.jp/","sec-ch-ua":"\"Not.A/Brand\";v=\"8\", \"Chromium\";v=\"114\", \"HeadlessChrome\";v=\"114\"","sec-ch-ua-mobile":"?0","sec-ch-ua-platform":"\"macOS\"","sec-fetch-dest":"image","sec-fetch-mode":"no-cors","sec-fetch-site":"cross-site","user-agent":"Mozilla/5.0 (Macintosh; Intel Mac OS X 10_15_7) AppleWebKit/537.36 (KHTML, like Gecko) HeadlessChrome/114.0.5735.35 Safari/537.36"},{":authority":"tshop.r10s.jp",":method":"GET",":path":"/paramountbed/logo/logo1.jpg?fitin=200:200",":scheme":"https","accept":"image/avif,image/webp,image/apng,image/svg+xml,image/*,*/*;q=0.8","accept-encoding":"gzip, deflate, br","referer":"https://www.rakuten.co.jp/","sec-ch-ua":"\"Not.A/Brand\";v=\"8\", \"Chromium\";v=\"114\", \"HeadlessChrome\";v=\"114\"","sec-ch-ua-mobile":"?0","sec-ch-ua-platform":"\"macOS\"","sec-fetch-dest":"image","sec-fetch-mode":"no-cors","sec-fetch-site":"cross-site","user-agent":"Mozilla/5.0 (Macintosh; Intel Mac OS X 10_15_7) AppleWebKit/537.36 (KHTML, like Gecko) HeadlessChrome/114.0.5735.35 Safari/537.36"},{":authority":"tshop.r10s.jp",":method":"GET",":path":"/shopch-r/logo/logo1.jpg?fitin=200:200",":scheme":"https","accept":"image/avif,image/webp,image/apng,image/svg+xml,image/*,*/*;q=0.8","accept-encoding":"gzip, deflate, br","referer":"https://www.rakuten.co.jp/","sec-ch-ua":"\"Not.A/Brand\";v=\"8\", \"Chromium\";v=\"114\", \"HeadlessChrome\";v=\"114\"","sec-ch-ua-mobile":"?0","sec-ch-ua-platform":"\"macOS\"","sec-fetch-dest":"image","sec-fetch-mode":"no-cors","sec-fetch-site":"cross-site","user-agent":"Mozilla/5.0 (Macintosh; Intel Mac OS X 10_15_7) AppleWebKit/537.36 (KHTML, like Gecko) HeadlessChrome/114.0.5735.35 Safari/537.36"},{":authority":"tshop.r10s.jp",":method":"GET",":path":"/apartbylowrys/logo/logo1.jpg?fitin=200:200",":scheme":"https","accept":"image/avif,image/webp,image/apng,image/svg+xml,image/*,*/*;q=0.8","accept-encoding":"gzip, deflate, br","referer":"https://www.rakuten.co.jp/","sec-ch-ua":"\"Not.A/Brand\";v=\"8\", \"Chromium\";v=\"114\", \"HeadlessChrome\";v=\"114\"","sec-ch-ua-mobile":"?0","sec-ch-ua-platform":"\"macOS\"","sec-fetch-dest":"image","sec-fetch-mode":"no-cors","sec-fetch-site":"cross-site","user-agent":"Mozilla/5.0 (Macintosh; Intel Mac OS X 10_15_7) AppleWebKit/537.36 (KHTML, like Gecko) HeadlessChrome/114.0.5735.35 Safari/537.36"},{":authority":"tshop.r10s.jp",":method":"GET",":path":"/noritz-official/logo/logo1.jpg?fitin=200:200",":scheme":"https","accept":"image/avif,image/webp,image/apng,image/svg+xml,image/*,*/*;q=0.8","accept-encoding":"gzip, deflate, br","referer":"https://www.rakuten.co.jp/","sec-ch-ua":"\"Not.A/Brand\";v=\"8\", \"Chromium\";v=\"114\", \"HeadlessChrome\";v=\"114\"","sec-ch-ua-mobile":"?0","sec-ch-ua-platform":"\"macOS\"","sec-fetch-dest":"image","sec-fetch-mode":"no-cors","sec-fetch-site":"cross-site","user-agent":"Mozilla/5.0 (Macintosh; Intel Mac OS X 10_15_7) AppleWebKit/537.36 (KHTML, like Gecko) HeadlessChrome/114.0.5735.35 Safari/537.36"},{":authority":"tshop.r10s.jp",":method":"GET",":path":"/daytona-outdoor/logo/logo1.jpg?fitin=200:200",":scheme":"https","accept":"image/avif,image/webp,image/apng,image/svg+xml,image/*,*/*;q=0.8","accept-encoding":"gzip, deflate, br","referer":"https://www.rakuten.co.jp/","sec-ch-ua":"\"Not.A/Brand\";v=\"8\", \"Chromium\";v=\"114\", \"HeadlessChrome\";v=\"114\"","sec-ch-ua-mobile":"?0","sec-ch-ua-platform":"\"macOS\"","sec-fetch-dest":"image","sec-fetch-mode":"no-cors","sec-fetch-site":"cross-site","user-agent":"Mozilla/5.0 (Macintosh; Intel Mac OS X 10_15_7) AppleWebKit/537.36 (KHTML, like Gecko) HeadlessChrome/114.0.5735.35 Safari/537.36"},{":authority":"tshop.r10s.jp",":method":"GET",":path":"/kaneka-milk/logo/logo1.jpg?fitin=200:200",":scheme":"https","accept":"image/avif,image/webp,image/apng,image/svg+xml,image/*,*/*;q=0.8","accept-encoding":"gzip, deflate, br","referer":"https://www.rakuten.co.jp/","sec-ch-ua":"\"Not.A/Brand\";v=\"8\", \"Chromium\";v=\"114\", \"HeadlessChrome\";v=\"114\"","sec-ch-ua-mobile":"?0","sec-ch-ua-platform":"\"macOS\"","sec-fetch-dest":"image","sec-fetch-mode":"no-cors","sec-fetch-site":"cross-site","user-agent":"Mozilla/5.0 (Macintosh; Intel Mac OS X 10_15_7) AppleWebKit/537.36 (KHTML, like Gecko) HeadlessChrome/114.0.5735.35 Safari/537.36"},{":authority":"tshop.r10s.jp",":method":"GET",":path":"/kidsonline/logo/logo1.jpg?fitin=200:200",":scheme":"https","accept":"image/avif,image/webp,image/apng,image/svg+xml,image/*,*/*;q=0.8","accept-encoding":"gzip, deflate, br","referer":"https://www.rakuten.co.jp/","sec-ch-ua":"\"Not.A/Brand\";v=\"8\", \"Chromium\";v=\"114\", \"HeadlessChrome\";v=\"114\"","sec-ch-ua-mobile":"?0","sec-ch-ua-platform":"\"macOS\"","sec-fetch-dest":"image","sec-fetch-mode":"no-cors","sec-fetch-site":"cross-site","user-agent":"Mozilla/5.0 (Macintosh; Intel Mac OS X 10_15_7) AppleWebKit/537.36 (KHTML, like Gecko) HeadlessChrome/114.0.5735.35 Safari/537.36"},{":authority":"s-ad.rmp.rakuten.co.jp",":method":"POST",":path":"/ad",":scheme":"https","accept":"application/json","accept-encoding":"gzip, deflate, br","cache-control":"max-age=0","content-length":"634","content-type":"text/plain","origin":"https://www.rakuten.co.jp","referer":"https://www.rakuten.co.jp/","sec-ch-ua":"\"Not.A/Brand\";v=\"8\", \"Chromium\";v=\"114\", \"HeadlessChrome\";v=\"114\"","sec-ch-ua-mobile":"?0","sec-ch-ua-platform":"\"macOS\"","sec-fetch-dest":"empty","sec-fetch-mode":"cors","sec-fetch-site":"same-site","user-agent":"Mozilla/5.0 (Macintosh; Intel Mac OS X 10_15_7) AppleWebKit/537.36 (KHTML, like Gecko) HeadlessChrome/114.0.5735.35 Safari/537.36"},{":authority":"cart-api.step.rakuten.co.jp",":method":"GET",":path":"/rms/mall/cart/jsonp/list/?sid=1010&callback=r2jsonp16861415641696465704957592149",":scheme":"https","accept":"*/*","accept-encoding":"gzip, deflate, br","referer":"https://www.rakuten.co.jp/","sec-ch-ua":"\"Not.A/Brand\";v=\"8\", \"Chromium\";v=\"114\", \"HeadlessChrome\";v=\"114\"","sec-ch-ua-mobile":"?0","sec-ch-ua-platform":"\"macOS\"","sec-fetch-dest":"script","sec-fetch-mode":"no-cors","sec-fetch-site":"same-site","user-agent":"Mozilla/5.0 (Macintosh; Intel Mac OS X 10_15_7) AppleWebKit/537.36 (KHTML, like Gecko) HeadlessChrome/114.0.5735.35 Safari/537.36"},{"accept":"*/*","accept-encoding":"gzip, deflate, br","connection":"keep-alive","content-length":"1086","content-type":"text/plain; charset=UTF-8","host":"rat.rakuten.co.jp","origin":"https://www.rakuten.co.jp","referer":"https://www.rakuten.co.jp/","sec-fetch-dest":"empty","sec-fetch-mode":"cors","sec-fetch-site":"same-site","user-agent":"Mozilla/5.0 (Macintosh; Intel Mac OS X 10_15_7) AppleWebKit/537.36 (KHTML, like Gecko) HeadlessChrome/114.0.5735.35 Safari/537.36","sec-ch-ua":"\"Not.A/Brand\";v=\"8\", \"Chromium\";v=\"114\", \"HeadlessChrome\";v=\"114\"","sec-ch-ua-mobile":"?0","sec-ch-ua-platform":"\"macOS\""},{":authority":"ashiato.rakuten.co.jp",":method":"GET",":path":"/rms/sd/ashiato/vc?act=6&sid=1&callback=jsonp1686141562305&_=1686141563900",":scheme":"https","accept":"*/*","accept-encoding":"gzip, deflate, br","referer":"https://www.rakuten.co.jp/","sec-ch-ua":"\"Not.A/Brand\";v=\"8\", \"Chromium\";v=\"114\", \"HeadlessChrome\";v=\"114\"","sec-ch-ua-mobile":"?0","sec-ch-ua-platform":"\"macOS\"","sec-fetch-dest":"script","sec-fetch-mode":"no-cors","sec-fetch-site":"same-site","user-agent":"Mozilla/5.0 (Macintosh; Intel Mac OS X 10_15_7) AppleWebKit/537.36 (KHTML, like Gecko) HeadlessChrome/114.0.5735.35 Safari/537.36"},{":authority":"ashiato.rakuten.co.jp",":method":"GET",":path":"/rms/sd/ashiato/vc?callback=jQuery112207200959599840737_1686141563962&act=6&k=3&sid=1&c=2&p=1&s=5&e=0&es=1&_=1686141563963",":scheme":"https","accept":"*/*","accept-encoding":"gzip, deflate, br","referer":"https://www.rakuten.co.jp/","sec-ch-ua":"\"Not.A/Brand\";v=\"8\", \"Chromium\";v=\"114\", \"HeadlessChrome\";v=\"114\"","sec-ch-ua-mobile":"?0","sec-ch-ua-platform":"\"macOS\"","sec-fetch-dest":"script","sec-fetch-mode":"no-cors","sec-fetch-site":"same-site","user-agent":"Mozilla/5.0 (Macintosh; Intel Mac OS X 10_15_7) AppleWebKit/537.36 (KHTML, like Gecko) HeadlessChrome/114.0.5735.35 Safari/537.36"},{":authority":"r.r10s.jp",":method":"GET",":path":"/com/js/d/ranking_liquid/1.5.1/ranking_liquid_multiple-1.5.1.min.js",":scheme":"https","accept":"*/*","accept-encoding":"gzip, deflate, br","referer":"https://www.rakuten.co.jp/","sec-ch-ua":"\"Not.A/Brand\";v=\"8\", \"Chromium\";v=\"114\", \"HeadlessChrome\";v=\"114\"","sec-ch-ua-mobile":"?0","sec-ch-ua-platform":"\"macOS\"","sec-fetch-dest":"script","sec-fetch-mode":"no-cors","sec-fetch-site":"cross-site","user-agent":"Mozilla/5.0 (Macintosh; Intel Mac OS X 10_15_7) AppleWebKit/537.36 (KHTML, like Gecko) HeadlessChrome/114.0.5735.35 Safari/537.36"},{"accept":"*/*","accept-encoding":"gzip, deflate, br","connection":"keep-alive","host":"user-attributes.api.rakuten.co.jp","origin":"https://www.rakuten.co.jp","referer":"https://www.rakuten.co.jp/","sec-fetch-dest":"empty","sec-fetch-mode":"cors","sec-fetch-site":"same-site","user-agent":"Mozilla/5.0 (Macintosh; Intel Mac OS X 10_15_7) AppleWebKit/537.36 (KHTML, like Gecko) HeadlessChrome/114.0.5735.35 Safari/537.36","sec-ch-ua":"\"Not.A/Brand\";v=\"8\", \"Chromium\";v=\"114\", \"HeadlessChrome\";v=\"114\"","sec-ch-ua-mobile":"?0","sec-ch-ua-platform":"\"macOS\""},{"accept":"*/*","accept-encoding":"gzip, deflate, br","connection":"keep-alive","host":"user-attributes.api.rakuten.co.jp","origin":"https://www.rakuten.co.jp","referer":"https://www.rakuten.co.jp/","sec-fetch-dest":"empty","sec-fetch-mode":"cors","sec-fetch-site":"same-site","user-agent":"Mozilla/5.0 (Macintosh; Intel Mac OS X 10_15_7) AppleWebKit/537.36 (KHTML, like Gecko) HeadlessChrome/114.0.5735.35 Safari/537.36","sec-ch-ua":"\"Not.A/Brand\";v=\"8\", \"Chromium\";v=\"114\", \"HeadlessChrome\";v=\"114\"","sec-ch-ua-mobile":"?0","sec-ch-ua-platform":"\"macOS\""},{"accept":"image/avif,image/webp,image/apng,image/svg+xml,image/*,*/*;q=0.8","accept-encoding":"gzip, deflate, br","connection":"keep-alive","host":"rt.rakuten.co.jp","referer":"https://www.rakuten.co.jp/","sec-fetch-dest":"image","sec-fetch-mode":"no-cors","sec-fetch-site":"same-site","user-agent":"Mozilla/5.0 (Macintosh; Intel Mac OS X 10_15_7) AppleWebKit/537.36 (KHTML, like Gecko) HeadlessChrome/114.0.5735.35 Safari/537.36","sec-ch-ua":"\"Not.A/Brand\";v=\"8\", \"Chromium\";v=\"114\", \"HeadlessChrome\";v=\"114\"","sec-ch-ua-mobile":"?0","sec-ch-ua-platform":"\"macOS\""},{":authority":"g01.api.bookmark.rakuten.co.jp",":method":"GET",":path":"/?callback=jQuery112207200959599840737_1686141563960&param2=20&_=1686141563961",":scheme":"https","accept":"*/*","accept-encoding":"gzip, deflate, br","referer":"https://www.rakuten.co.jp/","sec-ch-ua":"\"Not.A/Brand\";v=\"8\", \"Chromium\";v=\"114\", \"HeadlessChrome\";v=\"114\"","sec-ch-ua-mobile":"?0","sec-ch-ua-platform":"\"macOS\"","sec-fetch-dest":"script","sec-fetch-mode":"no-cors","sec-fetch-site":"same-site","user-agent":"Mozilla/5.0 (Macintosh; Intel Mac OS X 10_15_7) AppleWebKit/537.36 (KHTML, like Gecko) HeadlessChrome/114.0.5735.35 Safari/537.36"},{"accept":"*/*","accept-encoding":"gzip, deflate, br","connection":"keep-alive","host":"scview-content-high.api.rakuten.co.jp","referer":"https://www.rakuten.co.jp/","sec-fetch-dest":"script","sec-fetch-mode":"no-cors","sec-fetch-site":"same-site","user-agent":"Mozilla/5.0 (Macintosh; Intel Mac OS X 10_15_7) AppleWebKit/537.36 (KHTML, like Gecko) HeadlessChrome/114.0.5735.35 Safari/537.36","sec-ch-ua":"\"Not.A/Brand\";v=\"8\", \"Chromium\";v=\"114\", \"HeadlessChrome\";v=\"114\"","sec-ch-ua-mobile":"?0","sec-ch-ua-platform":"\"macOS\""},{":authority":"r.r10s.jp",":method":"GET",":path":"/com/inc/home/20080930/beta/tz/img/sprite/icon_sprite_09.png",":scheme":"https","accept":"image/avif,image/webp,image/apng,image/svg+xml,image/*,*/*;q=0.8","accept-encoding":"gzip, deflate, br","referer":"https://www.rakuten.co.jp/","sec-ch-ua":"\"Not.A/Brand\";v=\"8\", \"Chromium\";v=\"114\", \"HeadlessChrome\";v=\"114\"","sec-ch-ua-mobile":"?0","sec-ch-ua-platform":"\"macOS\"","sec-fetch-dest":"image","sec-fetch-mode":"no-cors","sec-fetch-site":"cross-site","user-agent":"Mozilla/5.0 (Macintosh; Intel Mac OS X 10_15_7) AppleWebKit/537.36 (KHTML, like Gecko) HeadlessChrome/114.0.5735.35 Safari/537.36"},{":authority":"r.r10s.jp",":method":"GET",":path":"/com/img/UXP/202305/js-banner-top/39d4cb11-6560-4122-83de-0a4af39d2e77/202306_ss_honban_09_top_js_314x314.gif",":scheme":"https","accept":"image/avif,image/webp,image/apng,image/svg+xml,image/*,*/*;q=0.8","accept-encoding":"gzip, deflate, br","referer":"https://www.rakuten.co.jp/","sec-ch-ua":"\"Not.A/Brand\";v=\"8\", \"Chromium\";v=\"114\", \"HeadlessChrome\";v=\"114\"","sec-ch-ua-mobile":"?0","sec-ch-ua-platform":"\"macOS\"","sec-fetch-dest":"image","sec-fetch-mode":"no-cors","sec-fetch-site":"cross-site","user-agent":"Mozilla/5.0 (Macintosh; Intel Mac OS X 10_15_7) AppleWebKit/537.36 (KHTML, like Gecko) HeadlessChrome/114.0.5735.35 Safari/537.36"},{":authority":"r.r10s.jp",":method":"GET",":path":"/com/img/UXP/202305/js-banner-top/a816e73e-249a-416a-a5d7-4f84206c633f/common_supersale_top_js_honban_nightcoupon_2_314x314.gif",":scheme":"https","accept":"image/avif,image/webp,image/apng,image/svg+xml,image/*,*/*;q=0.8","accept-encoding":"gzip, deflate, br","referer":"https://www.rakuten.co.jp/","sec-ch-ua":"\"Not.A/Brand\";v=\"8\", \"Chromium\";v=\"114\", \"HeadlessChrome\";v=\"114\"","sec-ch-ua-mobile":"?0","sec-ch-ua-platform":"\"macOS\"","sec-fetch-dest":"image","sec-fetch-mode":"no-cors","sec-fetch-site":"cross-site","user-agent":"Mozilla/5.0 (Macintosh; Intel Mac OS X 10_15_7) AppleWebKit/537.36 (KHTML, like Gecko) HeadlessChrome/114.0.5735.35 Safari/537.36"},{":authority":"r.r10s.jp",":method":"GET",":path":"/com/img/UXP/202302/js-banner-top/e61138f3-b74b-411a-bb8c-44ab1356c51e/14_JSTOP_NUAxSS_314x314px_honban-pc.gif",":scheme":"https","accept":"image/avif,image/webp,image/apng,image/svg+xml,image/*,*/*;q=0.8","accept-encoding":"gzip, deflate, br","referer":"https://www.rakuten.co.jp/","sec-ch-ua":"\"Not.A/Brand\";v=\"8\", \"Chromium\";v=\"114\", \"HeadlessChrome\";v=\"114\"","sec-ch-ua-mobile":"?0","sec-ch-ua-platform":"\"macOS\"","sec-fetch-dest":"image","sec-fetch-mode":"no-cors","sec-fetch-site":"cross-site","user-agent":"Mozilla/5.0 (Macintosh; Intel Mac OS X 10_15_7) AppleWebKit/537.36 (KHTML, like Gecko) HeadlessChrome/114.0.5735.35 Safari/537.36"},{":authority":"r.r10s.jp",":method":"GET",":path":"/com/img/UXP/202306/big-banner-top/172eea2c-583f-4eec-83a2-219526005161/202306_ss_bigbanner_honban09_UXP_1890x300.jpg",":scheme":"https","accept":"image/avif,image/webp,image/apng,image/svg+xml,image/*,*/*;q=0.8","accept-encoding":"gzip, deflate, br","referer":"https://www.rakuten.co.jp/","sec-ch-ua":"\"Not.A/Brand\";v=\"8\", \"Chromium\";v=\"114\", \"HeadlessChrome\";v=\"114\"","sec-ch-ua-mobile":"?0","sec-ch-ua-platform":"\"macOS\"","sec-fetch-dest":"image","sec-fetch-mode":"no-cors","sec-fetch-site":"cross-site","user-agent":"Mozilla/5.0 (Macintosh; Intel Mac OS X 10_15_7) AppleWebKit/537.36 (KHTML, like Gecko) HeadlessChrome/114.0.5735.35 Safari/537.36"},{":authority":"r.r10s.jp",":method":"GET",":path":"/com/img/UXP/202303/js-banner-top/2bf39ff5-6994-4658-8e2a-611671f518e6/JS_eagles.gif",":scheme":"https","accept":"image/avif,image/webp,image/apng,image/svg+xml,image/*,*/*;q=0.8","accept-encoding":"gzip, deflate, br","referer":"https://www.rakuten.co.jp/","sec-ch-ua":"\"Not.A/Brand\";v=\"8\", \"Chromium\";v=\"114\", \"HeadlessChrome\";v=\"114\"","sec-ch-ua-mobile":"?0","sec-ch-ua-platform":"\"macOS\"","sec-fetch-dest":"image","sec-fetch-mode":"no-cors","sec-fetch-site":"cross-site","user-agent":"Mozilla/5.0 (Macintosh; Intel Mac OS X 10_15_7) AppleWebKit/537.36 (KHTML, like Gecko) HeadlessChrome/114.0.5735.35 Safari/537.36"},{":authority":"r.r10s.jp",":method":"GET",":path":"/com/img/UXP/202305/js-banner-top/b7223db6-ca0d-4ffa-b61f-d229b78ba831/202306_ss_honban_07_top_js_314x314.gif",":scheme":"https","accept":"image/avif,image/webp,image/apng,image/svg+xml,image/*,*/*;q=0.8","accept-encoding":"gzip, deflate, br","referer":"https://www.rakuten.co.jp/","sec-ch-ua":"\"Not.A/Brand\";v=\"8\", \"Chromium\";v=\"114\", \"HeadlessChrome\";v=\"114\"","sec-ch-ua-mobile":"?0","sec-ch-ua-platform":"\"macOS\"","sec-fetch-dest":"image","sec-fetch-mode":"no-cors","sec-fetch-site":"cross-site","user-agent":"Mozilla/5.0 (Macintosh; Intel Mac OS X 10_15_7) AppleWebKit/537.36 (KHTML, like Gecko) HeadlessChrome/114.0.5735.35 Safari/537.36"}]}